PyBF/__init__.py
PyBF/reading.py
PyBF/writing.py
PyBinF-0.1.1.dist-info/LICENSE
PyBinF-0.1.1.dist-info/METADATA
PyBinF-0.1.1.dist-info/WHEEL
PyBinF-0.1.1.dist-info/top_level.txt
PyBinF-0.1.1.dist-info/RECORD
