Metadata-Version: 2.1
Name: PyBinF
Version: 0.1.1
Summary: Python binary files parser
Home-page: https://github.com/usr8820/PyBinF/
Author: Frank Lin
Author-email: W_126mail@126.com
License: UNKNOWN
Platform: UNKNOWN
Classifier: Programming Language :: Python :: 3
Classifier: License :: OSI Approved :: MIT License
Classifier: Operating System :: OS Independent
Requires-Python: >=3.0
Requires-Dist: PyErrs
